{
  "input_dir": "results/mia_v2_rq_fixed/pubmed/rq1_node_selection/hasi_default",
  "pattern": "*rq1_mia_v2*.json",
  "recursive": true,
  "num_files": 18,
  "num_groups": 6,
  "group_by": [
    "method",
    "dataset",
    "unlearning_type",
    "ratio",
    "selection"
  ],
  "metrics": [
    "metrics.utility.accuracy_after",
    "metrics.utility.accuracy_drop",
    "metrics.utility.f1_macro_after",
    "metrics.structure.degree_kl_divergence",
    "metrics.structure.clustering_coefficient_change",
    "metrics.structure.component_count_change",
    "metrics.privacy.medium_auc",
    "metrics.privacy.medium_train_size",
    "metrics.privacy.medium_eval_size",
    "metrics.privacy.strong_auc",
    "metrics.privacy.strong_auc_null_mean",
    "metrics.privacy.strong_auc_null_std",
    "metrics.privacy.strong_auc_pvalue",
    "metrics.privacy.privacy_score",
    "metrics.representation.embedding_l2_mean",
    "metrics.representation.member_embedding_l2_mean",
    "metrics.representation.neighbor_drift_mean",
    "metrics.efficiency.unlearn_time_seconds",
    "metrics.efficiency.online_wall_clock_seconds",
    "metrics.efficiency.offline_preprocessing_seconds"
  ],
  "summary": [
    {
      "method": "hasi_default_rq1_mia_v2",
      "dataset": "pubmed",
      "unlearning_type": "node",
      "ratio": 0.05,
      "selection": "hub_train",
      "n": 3,
      "seeds": [
        42,
        123,
        2024
      ],
      "paths": [
        "results/mia_v2_rq_fixed/pubmed/rq1_node_selection/hasi_default/hasi_default_rq1_mia_v2_pubmed_node_r0p05_hub_train_seed123.json",
        "results/mia_v2_rq_fixed/pubmed/rq1_node_selection/hasi_default/hasi_default_rq1_mia_v2_pubmed_node_r0p05_hub_train_seed2024.json",
        "results/mia_v2_rq_fixed/pubmed/rq1_node_selection/hasi_default/hasi_default_rq1_mia_v2_pubmed_node_r0p05_hub_train_seed42.json"
      ],
      "utility__accuracy_after_n": 3,
      "utility__accuracy_after_mean": 0.8718728870858689,
      "utility__accuracy_after_std": 0.003873035577210781,
      "utility__accuracy_after_min": 0.8676470588235294,
      "utility__accuracy_after_max": 0.8752535496957403,
      "utility__accuracy_drop_n": 3,
      "utility__accuracy_drop_mean": 0.0009296822177146854,
      "utility__accuracy_drop_std": 0.0016882170685800116,
      "utility__accuracy_drop_min": -0.0010141987829614951,
      "utility__accuracy_drop_max": 0.0020283975659229903,
      "utility__f1_macro_after_n": 3,
      "utility__f1_macro_after_mean": 0.8661331292912476,
      "utility__f1_macro_after_std": 0.0027507753671069425,
      "utility__f1_macro_after_min": 0.8629568327518102,
      "utility__f1_macro_after_max": 0.8677322475404764,
      "structure__degree_kl_divergence_n": 3,
      "structure__degree_kl_divergence_mean": 0.0058645319454151135,
      "structure__degree_kl_divergence_std": 0.0027802892680609714,
      "structure__degree_kl_divergence_min": 0.002738749439301626,
      "structure__degree_kl_divergence_max": 0.008061553474875038,
      "structure__clustering_coefficient_change_n": 3,
      "structure__clustering_coefficient_change_mean": 0.0005292966080143088,
      "structure__clustering_coefficient_change_std": 0.00016995951455351464,
      "structure__clustering_coefficient_change_min": 0.00034144822885211895,
      "structure__clustering_coefficient_change_max": 0.000672424216398064,
      "structure__component_count_change_n": 3,
      "structure__component_count_change_mean": 0.0,
      "structure__component_count_change_std": 0.0,
      "structure__component_count_change_min": 0.0,
      "structure__component_count_change_max": 0.0,
      "privacy__medium_auc_n": 3,
      "privacy__medium_auc_mean": 0.9892142987582178,
      "privacy__medium_auc_std": 0.00216106194083121,
      "privacy__medium_auc_min": 0.9872169466764061,
      "privacy__medium_auc_max": 0.9915084002921841,
      "privacy__medium_train_size_n": 3,
      "privacy__medium_train_size_mean": 592.0,
      "privacy__medium_train_size_std": 0.0,
      "privacy__medium_train_size_min": 592.0,
      "privacy__medium_train_size_max": 592.0,
      "privacy__medium_eval_size_n": 3,
      "privacy__medium_eval_size_mean": 592.0,
      "privacy__medium_eval_size_std": 0.0,
      "privacy__medium_eval_size_min": 592.0,
      "privacy__medium_eval_size_max": 592.0,
      "privacy__strong_auc_n": 3,
      "privacy__strong_auc_mean": 0.5769142241904066,
      "privacy__strong_auc_std": 0.014425270742329875,
      "privacy__strong_auc_min": 0.5649167960189919,
      "privacy__strong_auc_max": 0.5929196722059897,
      "privacy__strong_auc_null_mean_n": 3,
      "privacy__strong_auc_null_mean_mean": 0.5131871033829438,
      "privacy__strong_auc_null_mean_std": 0.0009465382179135994,
      "privacy__strong_auc_null_mean_min": 0.5121680828844046,
      "privacy__strong_auc_null_mean_max": 0.5140388599114317,
      "privacy__strong_auc_null_std_n": 3,
      "privacy__strong_auc_null_std_mean": 0.009969179883122079,
      "privacy__strong_auc_null_std_std": 0.0003244865752452964,
      "privacy__strong_auc_null_std_min": 0.009613817959122528,
      "privacy__strong_auc_null_std_max": 0.010249719800701445,
      "privacy__strong_auc_pvalue_n": 3,
      "privacy__strong_auc_pvalue_mean": 0.004975124378109453,
      "privacy__strong_auc_pvalue_std": 0.0,
      "privacy__strong_auc_pvalue_min": 0.004975124378109453,
      "privacy__strong_auc_pvalue_max": 0.004975124378109453,
      "privacy__privacy_score_n": 3,
      "privacy__privacy_score_mean": 0.8461715516191868,
      "privacy__privacy_score_std": 0.02885054148465975,
      "privacy__privacy_score_min": 0.8141606555880205,
      "privacy__privacy_score_max": 0.8701664079620162,
      "representation__embedding_l2_mean_n": 3,
      "representation__embedding_l2_mean_mean": 0.1985237685092157,
      "representation__embedding_l2_mean_std": 0.017961422600734564,
      "representation__embedding_l2_mean_min": 0.183529395089669,
      "representation__embedding_l2_mean_max": 0.21843019678157344,
      "representation__member_embedding_l2_mean_n": 3,
      "representation__member_embedding_l2_mean_mean": 0.5020863299387862,
      "representation__member_embedding_l2_mean_std": 0.01521719625230721,
      "representation__member_embedding_l2_mean_min": 0.4845597061405895,
      "representation__member_embedding_l2_mean_max": 0.5119341488496626,
      "representation__neighbor_drift_mean_n": 3,
      "representation__neighbor_drift_mean_mean": 0.22235754439998798,
      "representation__neighbor_drift_mean_std": 0.017301467686661826,
      "representation__neighbor_drift_mean_min": 0.20748306678809633,
      "representation__neighbor_drift_mean_max": 0.24134481441552816,
      "efficiency__unlearn_time_seconds_n": 3,
      "efficiency__unlearn_time_seconds_mean": 323.5444833656463,
      "efficiency__unlearn_time_seconds_std": 19.25884238698268,
      "efficiency__unlearn_time_seconds_min": 308.75651249010116,
      "efficiency__unlearn_time_seconds_max": 345.3221382978372,
      "efficiency__online_wall_clock_seconds_n": 3,
      "efficiency__online_wall_clock_seconds_mean": 334.9412810086117,
      "efficiency__online_wall_clock_seconds_std": 19.43093473571048,
      "efficiency__online_wall_clock_seconds_min": 319.99880564096384,
      "efficiency__online_wall_clock_seconds_max": 356.9074504659511,
      "efficiency__offline_preprocessing_seconds_n": 3,
      "efficiency__offline_preprocessing_seconds_mean": 0.9792091265941659,
      "efficiency__offline_preprocessing_seconds_std": 0.04340618700900169,
      "efficiency__offline_preprocessing_seconds_min": 0.9291051998734474,
      "efficiency__offline_preprocessing_seconds_max": 1.0053988359868526
    },
    {
      "method": "hasi_default_rq1_mia_v2",
      "dataset": "pubmed",
      "unlearning_type": "node",
      "ratio": 0.05,
      "selection": "low_degree_train",
      "n": 3,
      "seeds": [
        42,
        123,
        2024
      ],
      "paths": [
        "results/mia_v2_rq_fixed/pubmed/rq1_node_selection/hasi_default/hasi_default_rq1_mia_v2_pubmed_node_r0p05_low_degree_train_seed123.json",
        "results/mia_v2_rq_fixed/pubmed/rq1_node_selection/hasi_default/hasi_default_rq1_mia_v2_pubmed_node_r0p05_low_degree_train_seed2024.json",
        "results/mia_v2_rq_fixed/pubmed/rq1_node_selection/hasi_default/hasi_default_rq1_mia_v2_pubmed_node_r0p05_low_degree_train_seed42.json"
      ],
      "utility__accuracy_after_n": 3,
      "utility__accuracy_after_mean": 0.8551386071670047,
      "utility__accuracy_after_std": 0.017340525494566796,
      "utility__accuracy_after_min": 0.8351926977687627,
      "utility__accuracy_after_max": 0.8666328600405679,
      "utility__accuracy_drop_n": 3,
      "utility__accuracy_drop_mean": 0.017663962136578764,
      "utility__accuracy_drop_std": 0.02184405799672439,
      "utility__accuracy_drop_min": 0.0,
      "utility__accuracy_drop_max": 0.042089249492900604,
      "utility__f1_macro_after_n": 3,
      "utility__f1_macro_after_mean": 0.8503254300264161,
      "utility__f1_macro_after_std": 0.016455264246205283,
      "utility__f1_macro_after_min": 0.831360701042536,
      "utility__f1_macro_after_max": 0.8608226897535523,
      "structure__degree_kl_divergence_n": 3,
      "structure__degree_kl_divergence_mean": 0.016222459681425702,
      "structure__degree_kl_divergence_std": 0.002321521174469415,
      "structure__degree_kl_divergence_min": 0.014055398433721738,
      "structure__degree_kl_divergence_max": 0.01867249852882947,
      "structure__clustering_coefficient_change_n": 3,
      "structure__clustering_coefficient_change_mean": 0.0002778575751409343,
      "structure__clustering_coefficient_change_std": 2.3446909887783833e-05,
      "structure__clustering_coefficient_change_min": 0.0002641244593191705,
      "structure__clustering_coefficient_change_max": 0.00030493078370587984,
      "structure__component_count_change_n": 3,
      "structure__component_count_change_mean": 0.0,
      "structure__component_count_change_std": 0.0,
      "structure__component_count_change_min": 0.0,
      "structure__component_count_change_max": 0.0,
      "privacy__medium_auc_n": 3,
      "privacy__medium_auc_mean": 0.9600833942050159,
      "privacy__medium_auc_std": 0.022384129338413543,
      "privacy__medium_auc_min": 0.9452953798392988,
      "privacy__medium_auc_max": 0.9858359203798392,
      "privacy__medium_train_size_n": 3,
      "privacy__medium_train_size_mean": 592.0,
      "privacy__medium_train_size_std": 0.0,
      "privacy__medium_train_size_min": 592.0,
      "privacy__medium_train_size_max": 592.0,
      "privacy__medium_eval_size_n": 3,
      "privacy__medium_eval_size_mean": 592.0,
      "privacy__medium_eval_size_std": 0.0,
      "privacy__medium_eval_size_min": 592.0,
      "privacy__medium_eval_size_max": 592.0,
      "privacy__strong_auc_n": 3,
      "privacy__strong_auc_mean": 0.6481122169466764,
      "privacy__strong_auc_std": 0.014456675958660159,
      "privacy__strong_auc_min": 0.6314229136230826,
      "privacy__strong_auc_max": 0.6567664581811541,
      "privacy__strong_auc_null_mean_n": 3,
      "privacy__strong_auc_null_mean_mean": 0.5133750827474434,
      "privacy__strong_auc_null_mean_std": 0.0011094599390595353,
      "privacy__strong_auc_null_mean_min": 0.5121244692750183,
      "privacy__strong_auc_null_mean_max": 0.5142409634085099,
      "privacy__strong_auc_null_std_n": 3,
      "privacy__strong_auc_null_std_mean": 0.009711618116969382,
      "privacy__strong_auc_null_std_std": 0.0006007170417812023,
      "privacy__strong_auc_null_std_min": 0.009054127866704419,
      "privacy__strong_auc_null_std_max": 0.010231781350940201,
      "privacy__strong_auc_pvalue_n": 3,
      "privacy__strong_auc_pvalue_mean": 0.004975124378109453,
      "privacy__strong_auc_pvalue_std": 0.0,
      "privacy__strong_auc_pvalue_min": 0.004975124378109453,
      "privacy__strong_auc_pvalue_max": 0.004975124378109453,
      "privacy__privacy_score_n": 3,
      "privacy__privacy_score_mean": 0.7037755661066472,
      "privacy__privacy_score_std": 0.028913351917320317,
      "privacy__privacy_score_min": 0.6864670836376918,
      "privacy__privacy_score_max": 0.7371541727538349,
      "representation__embedding_l2_mean_n": 3,
      "representation__embedding_l2_mean_mean": 0.1251243321831596,
      "representation__embedding_l2_mean_std": 0.03172326970695441,
      "representation__embedding_l2_mean_min": 0.09717832439108705,
      "representation__embedding_l2_mean_max": 0.15960663463532004,
      "representation__member_embedding_l2_mean_n": 3,
      "representation__member_embedding_l2_mean_mean": 0.24786122695884938,
      "representation__member_embedding_l2_mean_std": 0.030619624204158823,
      "representation__member_embedding_l2_mean_min": 0.2198335543213504,
      "representation__member_embedding_l2_mean_max": 0.2805405008909473,
      "representation__neighbor_drift_mean_n": 3,
      "representation__neighbor_drift_mean_mean": 0.19193717674986888,
      "representation__neighbor_drift_mean_std": 0.05604351042271828,
      "representation__neighbor_drift_mean_min": 0.13232731017044586,
      "representation__neighbor_drift_mean_max": 0.24355662161533823,
      "efficiency__unlearn_time_seconds_n": 3,
      "efficiency__unlearn_time_seconds_mean": 9.349420470340798,
      "efficiency__unlearn_time_seconds_std": 0.05283052132159408,
      "efficiency__unlearn_time_seconds_min": 9.288499980000779,
      "efficiency__unlearn_time_seconds_max": 9.38263469003141,
      "efficiency__online_wall_clock_seconds_n": 3,
      "efficiency__online_wall_clock_seconds_mean": 15.73154451806719,
      "efficiency__online_wall_clock_seconds_std": 0.04773375215602194,
      "efficiency__online_wall_clock_seconds_min": 15.676870692055672,
      "efficiency__online_wall_clock_seconds_max": 15.764930452220142,
      "efficiency__offline_preprocessing_seconds_n": 3,
      "efficiency__offline_preprocessing_seconds_mean": 0.9792091265941659,
      "efficiency__offline_preprocessing_seconds_std": 0.04340618700900169,
      "efficiency__offline_preprocessing_seconds_min": 0.9291051998734474,
      "efficiency__offline_preprocessing_seconds_max": 1.0053988359868526
    },
    {
      "method": "hasi_default_rq1_mia_v2",
      "dataset": "pubmed",
      "unlearning_type": "node",
      "ratio": 0.05,
      "selection": "random_train",
      "n": 3,
      "seeds": [
        42,
        123,
        2024
      ],
      "paths": [
        "results/mia_v2_rq_fixed/pubmed/rq1_node_selection/hasi_default/hasi_default_rq1_mia_v2_pubmed_node_r0p05_random_train_seed123.json",
        "results/mia_v2_rq_fixed/pubmed/rq1_node_selection/hasi_default/hasi_default_rq1_mia_v2_pubmed_node_r0p05_random_train_seed2024.json",
        "results/mia_v2_rq_fixed/pubmed/rq1_node_selection/hasi_default/hasi_default_rq1_mia_v2_pubmed_node_r0p05_random_train_seed42.json"
      ],
      "utility__accuracy_after_n": 3,
      "utility__accuracy_after_mean": 0.8730561189993239,
      "utility__accuracy_after_std": 0.006584160481258362,
      "utility__accuracy_after_min": 0.8658722109533469,
      "utility__accuracy_after_max": 0.8788032454361054,
      "utility__accuracy_drop_n": 3,
      "utility__accuracy_drop_mean": -0.0002535496957403553,
      "utility__accuracy_drop_std": 0.0011619106731632005,
      "utility__accuracy_drop_min": -0.0015212981744421317,
      "utility__accuracy_drop_max": 0.0007606490872210658,
      "utility__f1_macro_after_n": 3,
      "utility__f1_macro_after_mean": 0.865003632557316,
      "utility__f1_macro_after_std": 0.005046976209085023,
      "utility__f1_macro_after_min": 0.8594040725071223,
      "utility__f1_macro_after_max": 0.8692018632566505,
      "structure__degree_kl_divergence_n": 3,
      "structure__degree_kl_divergence_mean": 0.012832645642888807,
      "structure__degree_kl_divergence_std": 0.0014479548880280985,
      "structure__degree_kl_divergence_min": 0.011227671404489072,
      "structure__degree_kl_divergence_max": 0.01404086250997433,
      "structure__clustering_coefficient_change_n": 3,
      "structure__clustering_coefficient_change_mean": 0.0003469524787318272,
      "structure__clustering_coefficient_change_std": 0.00010913978308565027,
      "structure__clustering_coefficient_change_min": 0.0002532939463207942,
      "structure__clustering_coefficient_change_max": 0.0004668060678163777,
      "structure__component_count_change_n": 3,
      "structure__component_count_change_mean": 0.0,
      "structure__component_count_change_std": 0.0,
      "structure__component_count_change_min": 0.0,
      "structure__component_count_change_max": 0.0,
      "privacy__medium_auc_n": 3,
      "privacy__medium_auc_mean": 0.9787253469685901,
      "privacy__medium_auc_std": 0.010138225804018209,
      "privacy__medium_auc_min": 0.9709642074506939,
      "privacy__medium_auc_max": 0.9901958546384222,
      "privacy__medium_train_size_n": 3,
      "privacy__medium_train_size_mean": 592.0,
      "privacy__medium_train_size_std": 0.0,
      "privacy__medium_train_size_min": 592.0,
      "privacy__medium_train_size_max": 592.0,
      "privacy__medium_eval_size_n": 3,
      "privacy__medium_eval_size_mean": 592.0,
      "privacy__medium_eval_size_std": 0.0,
      "privacy__medium_eval_size_min": 592.0,
      "privacy__medium_eval_size_max": 592.0,
      "privacy__strong_auc_n": 3,
      "privacy__strong_auc_mean": 0.6096070732895057,
      "privacy__strong_auc_std": 0.022283562836967894,
      "privacy__strong_auc_min": 0.5859774470416362,
      "privacy__strong_auc_max": 0.6302416225346968,
      "privacy__strong_auc_null_mean_n": 3,
      "privacy__strong_auc_null_mean_mean": 0.5136452816837108,
      "privacy__strong_auc_null_mean_std": 0.001153431288826086,
      "privacy__strong_auc_null_mean_min": 0.5127134456035428,
      "privacy__strong_auc_null_mean_max": 0.5149353143261505,
      "privacy__strong_auc_null_std_n": 3,
      "privacy__strong_auc_null_std_mean": 0.010534816407663038,
      "privacy__strong_auc_null_std_std": 0.00034532300949822455,
      "privacy__strong_auc_null_std_min": 0.01022684161953397,
      "privacy__strong_auc_null_std_max": 0.010908147432354387,
      "privacy__strong_auc_pvalue_n": 3,
      "privacy__strong_auc_pvalue_mean": 0.004975124378109453,
      "privacy__strong_auc_pvalue_std": 0.0,
      "privacy__strong_auc_pvalue_min": 0.004975124378109453,
      "privacy__strong_auc_pvalue_max": 0.004975124378109453,
      "privacy__privacy_score_n": 3,
      "privacy__privacy_score_mean": 0.7807858534209885,
      "privacy__privacy_score_std": 0.04456712567393579,
      "privacy__privacy_score_min": 0.7395167549306063,
      "privacy__privacy_score_max": 0.8280451059167275,
      "representation__embedding_l2_mean_n": 3,
      "representation__embedding_l2_mean_mean": 0.1122700730273062,
      "representation__embedding_l2_mean_std": 0.038480802620874,
      "representation__embedding_l2_mean_min": 0.07212626153520957,
      "representation__embedding_l2_mean_max": 0.1488382804653072,
      "representation__member_embedding_l2_mean_n": 3,
      "representation__member_embedding_l2_mean_mean": 0.281470871273586,
      "representation__member_embedding_l2_mean_std": 0.028812627478767037,
      "representation__member_embedding_l2_mean_min": 0.25129410191034546,
      "representation__member_embedding_l2_mean_max": 0.30869142168637487,
      "representation__neighbor_drift_mean_n": 3,
      "representation__neighbor_drift_mean_mean": 0.14789814836938206,
      "representation__neighbor_drift_mean_std": 0.03910194197810313,
      "representation__neighbor_drift_mean_min": 0.10774484647898273,
      "representation__neighbor_drift_mean_max": 0.18585624575866963,
      "efficiency__unlearn_time_seconds_n": 3,
      "efficiency__unlearn_time_seconds_mean": 33.516619977696486,
      "efficiency__unlearn_time_seconds_std": 14.613341067705894,
      "efficiency__unlearn_time_seconds_min": 20.141184996115044,
      "efficiency__unlearn_time_seconds_max": 49.113492392003536,
      "efficiency__online_wall_clock_seconds_n": 3,
      "efficiency__online_wall_clock_seconds_mean": 40.07263788635222,
      "efficiency__online_wall_clock_seconds_std": 14.714395827391051,
      "efficiency__online_wall_clock_seconds_min": 26.67555877007544,
      "efficiency__online_wall_clock_seconds_max": 55.82115799305029,
      "efficiency__offline_preprocessing_seconds_n": 3,
      "efficiency__offline_preprocessing_seconds_mean": 0.9792091265941659,
      "efficiency__offline_preprocessing_seconds_std": 0.04340618700900169,
      "efficiency__offline_preprocessing_seconds_min": 0.9291051998734474,
      "efficiency__offline_preprocessing_seconds_max": 1.0053988359868526
    },
    {
      "method": "hasi_default_rq1_mia_v2",
      "dataset": "pubmed",
      "unlearning_type": "node",
      "ratio": 0.1,
      "selection": "hub_train",
      "n": 3,
      "seeds": [
        42,
        123,
        2024
      ],
      "paths": [
        "results/mia_v2_rq_fixed/pubmed/rq1_node_selection/hasi_default/hasi_default_rq1_mia_v2_pubmed_node_r0p1_hub_train_seed123.json",
        "results/mia_v2_rq_fixed/pubmed/rq1_node_selection/hasi_default/hasi_default_rq1_mia_v2_pubmed_node_r0p1_hub_train_seed2024.json",
        "results/mia_v2_rq_fixed/pubmed/rq1_node_selection/hasi_default/hasi_default_rq1_mia_v2_pubmed_node_r0p1_hub_train_seed42.json"
      ],
      "utility__accuracy_after_n": 3,
      "utility__accuracy_after_mean": 0.8706896551724137,
      "utility__accuracy_after_std": 0.003237105815112473,
      "utility__accuracy_after_min": 0.8671399594320487,
      "utility__accuracy_after_max": 0.8734787018255578,
      "utility__accuracy_drop_n": 3,
      "utility__accuracy_drop_mean": 0.002112914131169726,
      "utility__accuracy_drop_std": 0.002300652060313795,
      "utility__accuracy_drop_min": -0.0005070993914807476,
      "utility__accuracy_drop_max": 0.003803245436105551,
      "utility__f1_macro_after_n": 3,
      "utility__f1_macro_after_mean": 0.8658992953154477,
      "utility__f1_macro_after_std": 0.0025952613246044225,
      "utility__f1_macro_after_min": 0.8629362274790727,
      "utility__f1_macro_after_max": 0.867768840948365,
      "structure__degree_kl_divergence_n": 3,
      "structure__degree_kl_divergence_mean": 0.009065382874703761,
      "structure__degree_kl_divergence_std": 0.004446115393045144,
      "structure__degree_kl_divergence_min": 0.003931588616333289,
      "structure__degree_kl_divergence_max": 0.01166482954789116,
      "structure__clustering_coefficient_change_n": 3,
      "structure__clustering_coefficient_change_mean": 0.0005386746795902573,
      "structure__clustering_coefficient_change_std": 0.00010481931763439569,
      "structure__clustering_coefficient_change_min": 0.0004219653887469893,
      "structure__clustering_coefficient_change_max": 0.0006248015309467184,
      "structure__component_count_change_n": 3,
      "structure__component_count_change_mean": 0.0,
      "structure__component_count_change_std": 0.0,
      "structure__component_count_change_min": 0.0,
      "structure__component_count_change_max": 0.0,
      "privacy__medium_auc_n": 3,
      "privacy__medium_auc_mean": 0.9945158418553689,
      "privacy__medium_auc_std": 0.0022544091132512736,
      "privacy__medium_auc_min": 0.9919506711102994,
      "privacy__medium_auc_max": 0.9961822041636231,
      "privacy__medium_train_size_n": 3,
      "privacy__medium_train_size_mean": 1182.0,
      "privacy__medium_train_size_std": 0.0,
      "privacy__medium_train_size_min": 1182.0,
      "privacy__medium_train_size_max": 1182.0,
      "privacy__medium_eval_size_n": 3,
      "privacy__medium_eval_size_mean": 1184.0,
      "privacy__medium_eval_size_std": 0.0,
      "privacy__medium_eval_size_min": 1184.0,
      "privacy__medium_eval_size_max": 1184.0,
      "privacy__strong_auc_n": 3,
      "privacy__strong_auc_mean": 0.5293848921523022,
      "privacy__strong_auc_std": 0.02235153787606718,
      "privacy__strong_auc_min": 0.5036902755219941,
      "privacy__strong_auc_max": 0.5443372545264735,
      "privacy__strong_auc_null_mean_n": 3,
      "privacy__strong_auc_null_mean_mean": 0.5095233010048669,
      "privacy__strong_auc_null_mean_std": 0.0005019318020953795,
      "privacy__strong_auc_null_mean_min": 0.5090171055292325,
      "privacy__strong_auc_null_mean_max": 0.5100208576130287,
      "privacy__strong_auc_null_std_n": 3,
      "privacy__strong_auc_null_std_mean": 0.007144453460970232,
      "privacy__strong_auc_null_std_std": 0.0005645187115870054,
      "privacy__strong_auc_null_std_min": 0.006508400736705498,
      "privacy__strong_auc_null_std_max": 0.007586007450370391,
      "privacy__strong_auc_pvalue_n": 3,
      "privacy__strong_auc_pvalue_mean": 0.2653399668325041,
      "privacy__strong_auc_pvalue_std": 0.4509651356356778,
      "privacy__strong_auc_pvalue_min": 0.004975124378109453,
      "privacy__strong_auc_pvalue_max": 0.7860696517412935,
      "privacy__privacy_score_n": 3,
      "privacy__privacy_score_mean": 0.9412302156953954,
      "privacy__privacy_score_std": 0.04470307575213436,
      "privacy__privacy_score_min": 0.911325490947053,
      "privacy__privacy_score_max": 0.9926194489560118,
      "representation__embedding_l2_mean_n": 3,
      "representation__embedding_l2_mean_mean": 0.20005190590439023,
      "representation__embedding_l2_mean_std": 0.003802614068907504,
      "representation__embedding_l2_mean_min": 0.1960875620011721,
      "representation__embedding_l2_mean_max": 0.20366896525879383,
      "representation__member_embedding_l2_mean_n": 3,
      "representation__member_embedding_l2_mean_mean": 0.5664291733931697,
      "representation__member_embedding_l2_mean_std": 0.019161008088970016,
      "representation__member_embedding_l2_mean_min": 0.5470381568148126,
      "representation__member_embedding_l2_mean_max": 0.5853515765028707,
      "representation__neighbor_drift_mean_n": 3,
      "representation__neighbor_drift_mean_mean": 0.203054099772792,
      "representation__neighbor_drift_mean_std": 0.0028393653439505377,
      "representation__neighbor_drift_mean_min": 0.20089871597058256,
      "representation__neighbor_drift_mean_max": 0.2062713561284779,
      "efficiency__unlearn_time_seconds_n": 3,
      "efficiency__unlearn_time_seconds_mean": 413.763078180685,
      "efficiency__unlearn_time_seconds_std": 17.8975511293826,
      "efficiency__unlearn_time_seconds_min": 403.04598524817266,
      "efficiency__unlearn_time_seconds_max": 434.4245745500084,
      "efficiency__online_wall_clock_seconds_n": 3,
      "efficiency__online_wall_clock_seconds_mean": 426.5145440342215,
      "efficiency__online_wall_clock_seconds_std": 18.50998396342759,
      "efficiency__online_wall_clock_seconds_min": 415.3698993078433,
      "efficiency__online_wall_clock_seconds_max": 447.8813963609282,
      "efficiency__offline_preprocessing_seconds_n": 3,
      "efficiency__offline_preprocessing_seconds_mean": 0.9792091265941659,
      "efficiency__offline_preprocessing_seconds_std": 0.04340618700900169,
      "efficiency__offline_preprocessing_seconds_min": 0.9291051998734474,
      "efficiency__offline_preprocessing_seconds_max": 1.0053988359868526
    },
    {
      "method": "hasi_default_rq1_mia_v2",
      "dataset": "pubmed",
      "unlearning_type": "node",
      "ratio": 0.1,
      "selection": "low_degree_train",
      "n": 3,
      "seeds": [
        42,
        123,
        2024
      ],
      "paths": [
        "results/mia_v2_rq_fixed/pubmed/rq1_node_selection/hasi_default/hasi_default_rq1_mia_v2_pubmed_node_r0p1_low_degree_train_seed123.json",
        "results/mia_v2_rq_fixed/pubmed/rq1_node_selection/hasi_default/hasi_default_rq1_mia_v2_pubmed_node_r0p1_low_degree_train_seed2024.json",
        "results/mia_v2_rq_fixed/pubmed/rq1_node_selection/hasi_default/hasi_default_rq1_mia_v2_pubmed_node_r0p1_low_degree_train_seed42.json"
      ],
      "utility__accuracy_after_n": 3,
      "utility__accuracy_after_mean": 0.8668864097363084,
      "utility__accuracy_after_std": 0.009257168490633239,
      "utility__accuracy_after_min": 0.8564908722109533,
      "utility__accuracy_after_max": 0.8742393509127789,
      "utility__accuracy_drop_n": 3,
      "utility__accuracy_drop_mean": 0.005916159567275166,
      "utility__accuracy_drop_std": 0.005098387806577335,
      "utility__accuracy_drop_min": 0.00025354969574031827,
      "utility__accuracy_drop_max": 0.010141987829614618,
      "utility__f1_macro_after_n": 3,
      "utility__f1_macro_after_mean": 0.8597181295474755,
      "utility__f1_macro_after_std": 0.008330320901966861,
      "utility__f1_macro_after_min": 0.8507436193077784,
      "utility__f1_macro_after_max": 0.8672033624520857,
      "structure__degree_kl_divergence_n": 3,
      "structure__degree_kl_divergence_mean": 0.015940745833382768,
      "structure__degree_kl_divergence_std": 0.003429342579784219,
      "structure__degree_kl_divergence_min": 0.011990320600433785,
      "structure__degree_kl_divergence_max": 0.018152592954275053,
      "structure__clustering_coefficient_change_n": 3,
      "structure__clustering_coefficient_change_mean": 0.0003484504817545947,
      "structure__clustering_coefficient_change_std": 0.00018140021521671117,
      "structure__clustering_coefficient_change_min": 0.00014211579913298023,
      "structure__clustering_coefficient_change_max": 0.0004828514130167244,
      "structure__component_count_change_n": 3,
      "structure__component_count_change_mean": 0.0,
      "structure__component_count_change_std": 0.0,
      "structure__component_count_change_min": 0.0,
      "structure__component_count_change_max": 0.0,
      "privacy__medium_auc_n": 3,
      "privacy__medium_auc_mean": 0.9752318830654979,
      "privacy__medium_auc_std": 0.012330112373401292,
      "privacy__medium_auc_min": 0.9616679601899196,
      "privacy__medium_auc_max": 0.9857617330168006,
      "privacy__medium_train_size_n": 3,
      "privacy__medium_train_size_mean": 1182.0,
      "privacy__medium_train_size_std": 0.0,
      "privacy__medium_train_size_min": 1182.0,
      "privacy__medium_train_size_max": 1182.0,
      "privacy__medium_eval_size_n": 3,
      "privacy__medium_eval_size_mean": 1184.0,
      "privacy__medium_eval_size_std": 0.0,
      "privacy__medium_eval_size_min": 1184.0,
      "privacy__medium_eval_size_max": 1184.0,
      "privacy__strong_auc_n": 3,
      "privacy__strong_auc_mean": 0.6651056206944106,
      "privacy__strong_auc_std": 0.0366815195610599,
      "privacy__strong_auc_min": 0.6272232221903852,
      "privacy__strong_auc_max": 0.7004549517716824,
      "privacy__strong_auc_null_mean_n": 3,
      "privacy__strong_auc_null_mean_mean": 0.5090644823455799,
      "privacy__strong_auc_null_mean_std": 0.00031732874005886295,
      "privacy__strong_auc_null_mean_min": 0.5087074425022275,
      "privacy__strong_auc_null_mean_max": 0.509314342592189,
      "privacy__strong_auc_null_std_n": 3,
      "privacy__strong_auc_null_std_mean": 0.006704305804484951,
      "privacy__strong_auc_null_std_std": 0.00020406930338018325,
      "privacy__strong_auc_null_std_min": 0.006568667850602278,
      "privacy__strong_auc_null_std_max": 0.0069389961081483,
      "privacy__strong_auc_pvalue_n": 3,
      "privacy__strong_auc_pvalue_mean": 0.004975124378109453,
      "privacy__strong_auc_pvalue_std": 0.0,
      "privacy__strong_auc_pvalue_min": 0.004975124378109453,
      "privacy__strong_auc_pvalue_max": 0.004975124378109453,
      "privacy__privacy_score_n": 3,
      "privacy__privacy_score_mean": 0.6697887586111788,
      "privacy__privacy_score_std": 0.0733630391221198,
      "privacy__privacy_score_min": 0.5990900964566352,
      "privacy__privacy_score_max": 0.7455535556192296,
      "representation__embedding_l2_mean_n": 3,
      "representation__embedding_l2_mean_mean": 0.11234719557738508,
      "representation__embedding_l2_mean_std": 0.0219731416058389,
      "representation__embedding_l2_mean_min": 0.08736396139801801,
      "representation__embedding_l2_mean_max": 0.12867253924631591,
      "representation__member_embedding_l2_mean_n": 3,
      "representation__member_embedding_l2_mean_mean": 0.23776305233339956,
      "representation__member_embedding_l2_mean_std": 0.009514491739444011,
      "representation__member_embedding_l2_mean_min": 0.2267867121072661,
      "representation__member_embedding_l2_mean_max": 0.24365806331224993,
      "representation__neighbor_drift_mean_n": 3,
      "representation__neighbor_drift_mean_mean": 0.18702012991017894,
      "representation__neighbor_drift_mean_std": 0.033127913220246705,
      "representation__neighbor_drift_mean_min": 0.1508442353043615,
      "representation__neighbor_drift_mean_max": 0.21587548736733495,
      "efficiency__unlearn_time_seconds_n": 3,
      "efficiency__unlearn_time_seconds_mean": 9.305602731260782,
      "efficiency__unlearn_time_seconds_std": 0.14073128927171552,
      "efficiency__unlearn_time_seconds_min": 9.192870733095333,
      "efficiency__unlearn_time_seconds_max": 9.463329068850726,
      "efficiency__online_wall_clock_seconds_n": 3,
      "efficiency__online_wall_clock_seconds_mean": 15.654092352914935,
      "efficiency__online_wall_clock_seconds_std": 0.16013263193872504,
      "efficiency__online_wall_clock_seconds_min": 15.501422206871212,
      "efficiency__online_wall_clock_seconds_max": 15.820767503930256,
      "efficiency__offline_preprocessing_seconds_n": 3,
      "efficiency__offline_preprocessing_seconds_mean": 0.9792091265941659,
      "efficiency__offline_preprocessing_seconds_std": 0.04340618700900169,
      "efficiency__offline_preprocessing_seconds_min": 0.9291051998734474,
      "efficiency__offline_preprocessing_seconds_max": 1.0053988359868526
    },
    {
      "method": "hasi_default_rq1_mia_v2",
      "dataset": "pubmed",
      "unlearning_type": "node",
      "ratio": 0.1,
      "selection": "random_train",
      "n": 3,
      "seeds": [
        42,
        123,
        2024
      ],
      "paths": [
        "results/mia_v2_rq_fixed/pubmed/rq1_node_selection/hasi_default/hasi_default_rq1_mia_v2_pubmed_node_r0p1_random_train_seed123.json",
        "results/mia_v2_rq_fixed/pubmed/rq1_node_selection/hasi_default/hasi_default_rq1_mia_v2_pubmed_node_r0p1_random_train_seed2024.json",
        "results/mia_v2_rq_fixed/pubmed/rq1_node_selection/hasi_default/hasi_default_rq1_mia_v2_pubmed_node_r0p1_random_train_seed42.json"
      ],
      "utility__accuracy_after_n": 3,
      "utility__accuracy_after_mean": 0.8722954699121028,
      "utility__accuracy_after_std": 0.012479007521197343,
      "utility__accuracy_after_min": 0.8580121703853956,
      "utility__accuracy_after_max": 0.8810851926977687,
      "utility__accuracy_drop_n": 3,
      "utility__accuracy_drop_mean": 0.0005070993914807106,
      "utility__accuracy_drop_std": 0.007031148389382359,
      "utility__accuracy_drop_min": -0.00380324543610544,
      "utility__accuracy_drop_max": 0.008620689655172376,
      "utility__f1_macro_after_n": 3,
      "utility__f1_macro_after_mean": 0.8660808934803911,
      "utility__f1_macro_after_std": 0.010925212257015,
      "utility__f1_macro_after_min": 0.8534918805084869,
      "utility__f1_macro_after_max": 0.8730809686417769,
      "structure__degree_kl_divergence_n": 3,
      "structure__degree_kl_divergence_mean": 0.014716044878039467,
      "structure__degree_kl_divergence_std": 0.001630671556951784,
      "structure__degree_kl_divergence_min": 0.013122185848052786,
      "structure__degree_kl_divergence_max": 0.016381190824027402,
      "structure__clustering_coefficient_change_n": 3,
      "structure__clustering_coefficient_change_mean": 0.0005000984532917188,
      "structure__clustering_coefficient_change_std": 8.359835324504565e-05,
      "structure__clustering_coefficient_change_min": 0.00040603199671371965,
      "structure__clustering_coefficient_change_max": 0.0005659016303134132,
      "structure__component_count_change_n": 3,
      "structure__component_count_change_mean": 0.0,
      "structure__component_count_change_std": 0.0,
      "structure__component_count_change_min": 0.0,
      "structure__component_count_change_max": 0.0,
      "privacy__medium_auc_n": 3,
      "privacy__medium_auc_mean": 0.9613017789749209,
      "privacy__medium_auc_std": 0.0192817097934463,
      "privacy__medium_auc_min": 0.9430269585463842,
      "privacy__medium_auc_max": 0.9814531592403214,
      "privacy__medium_train_size_n": 3,
      "privacy__medium_train_size_mean": 1182.0,
      "privacy__medium_train_size_std": 0.0,
      "privacy__medium_train_size_min": 1182.0,
      "privacy__medium_train_size_max": 1182.0,
      "privacy__medium_eval_size_n": 3,
      "privacy__medium_eval_size_mean": 1184.0,
      "privacy__medium_eval_size_std": 0.0,
      "privacy__medium_eval_size_min": 1184.0,
      "privacy__medium_eval_size_max": 1184.0,
      "privacy__strong_auc_n": 3,
      "privacy__strong_auc_mean": 0.6388350795659463,
      "privacy__strong_auc_std": 0.0321127960169204,
      "privacy__strong_auc_min": 0.6112359582676248,
      "privacy__strong_auc_max": 0.6740810395794465,
      "privacy__strong_auc_null_mean_n": 3,
      "privacy__strong_auc_null_mean_mean": 0.509642290864737,
      "privacy__strong_auc_null_mean_std": 0.00023384781453167618,
      "privacy__strong_auc_null_mean_min": 0.5093728103614962,
      "privacy__strong_auc_null_mean_max": 0.5097918633158245,
      "privacy__strong_auc_null_std_n": 3,
      "privacy__strong_auc_null_std_mean": 0.007407036456756877,
      "privacy__strong_auc_null_std_std": 8.896346661224186e-05,
      "privacy__strong_auc_null_std_min": 0.007304726876665284,
      "privacy__strong_auc_null_std_max": 0.0074661950432630365,
      "privacy__strong_auc_pvalue_n": 3,
      "privacy__strong_auc_pvalue_mean": 0.004975124378109453,
      "privacy__strong_auc_pvalue_std": 0.0,
      "privacy__strong_auc_pvalue_min": 0.004975124378109453,
      "privacy__strong_auc_pvalue_max": 0.004975124378109453,
      "privacy__privacy_score_n": 3,
      "privacy__privacy_score_mean": 0.7223298408681074,
      "privacy__privacy_score_std": 0.0642255920338408,
      "privacy__privacy_score_min": 0.6518379208411069,
      "privacy__privacy_score_max": 0.7775280834647504,
      "representation__embedding_l2_mean_n": 3,
      "representation__embedding_l2_mean_mean": 0.1408287619657088,
      "representation__embedding_l2_mean_std": 0.028786133235335878,
      "representation__embedding_l2_mean_min": 0.10890583401639083,
      "representation__embedding_l2_mean_max": 0.16481122774809098,
      "representation__member_embedding_l2_mean_n": 3,
      "representation__member_embedding_l2_mean_mean": 0.2903798649660932,
      "representation__member_embedding_l2_mean_std": 0.014333088365477186,
      "representation__member_embedding_l2_mean_min": 0.2746133491007647,
      "representation__member_embedding_l2_mean_max": 0.3026220396442156,
      "representation__neighbor_drift_mean_n": 3,
      "representation__neighbor_drift_mean_mean": 0.17870619162746246,
      "representation__neighbor_drift_mean_std": 0.0321352102175886,
      "representation__neighbor_drift_mean_min": 0.14255466106970774,
      "representation__neighbor_drift_mean_max": 0.20402570348372684,
      "efficiency__unlearn_time_seconds_n": 3,
      "efficiency__unlearn_time_seconds_mean": 54.67305972403847,
      "efficiency__unlearn_time_seconds_std": 23.849136738314698,
      "efficiency__unlearn_time_seconds_min": 34.26330317812972,
      "efficiency__unlearn_time_seconds_max": 80.88926840596832,
      "efficiency__online_wall_clock_seconds_n": 3,
      "efficiency__online_wall_clock_seconds_mean": 61.6035162829794,
      "efficiency__online_wall_clock_seconds_std": 24.283995591868354,
      "efficiency__online_wall_clock_seconds_min": 40.93314594682306,
      "efficiency__online_wall_clock_seconds_max": 88.34797579608858,
      "efficiency__offline_preprocessing_seconds_n": 3,
      "efficiency__offline_preprocessing_seconds_mean": 0.9792091265941659,
      "efficiency__offline_preprocessing_seconds_std": 0.04340618700900169,
      "efficiency__offline_preprocessing_seconds_min": 0.9291051998734474,
      "efficiency__offline_preprocessing_seconds_max": 1.0053988359868526
    }
  ],
  "skipped": []
}
